pppmodels/__init__.py
pppmodels/prophet.py
pppmodels-0.9.0.dist-info/METADATA
pppmodels-0.9.0.dist-info/WHEEL
pppmodels-0.9.0.dist-info/licenses/LICENSE
pppmodels-0.9.0.dist-info/RECORD
