Metadata-Version: 2.3
Name: pppmodels
Version: 0.9.0
Summary: Add your description here
Author-email: galenseilis <galen.seilis@seilis.ca>
License-File: LICENSE
Requires-Python: >=3.10
Requires-Dist: pppmodels>=0.6.0
Requires-Dist: pymc>=5.16.1
